symbols/__init__.py
symbols/c_executor.py
symbolslang-1.0.4.dist-info/licenses/LICENSE
symbolslang-1.0.4.dist-info/METADATA
symbolslang-1.0.4.dist-info/WHEEL
symbolslang-1.0.4.dist-info/entry_points.txt
symbolslang-1.0.4.dist-info/top_level.txt
symbolslang-1.0.4.dist-info/RECORD
